pygov_br/__init__.py
pygov_br/__main__.py
pygov_br/__meta__.py
pygov_br/base.py
pygov_br/exceptions.py
pygov_br/camara_deputados/__init__.py
pygov_br/camara_deputados/deputy.py
pygov_br/camara_deputados/legislative_body.py
pygov_br/camara_deputados/proposal.py
pygov_br/camara_deputados/session.py
pygov_br/django_apps/__init__.py
pygov_br/django_apps/base.py
pygov_br/django_apps/camara_deputados/__init__.py
pygov_br/django_apps/camara_deputados/models.py
pygov_br/django_apps/camara_deputados/data_importer/__init__.py
pygov_br/django_apps/camara_deputados/data_importer/deputy.py
pygov_br/django_apps/camara_deputados/data_importer/legislative_body.py
pygov_br/django_apps/camara_deputados/data_importer/proposal.py
pygov_br/django_apps/camara_deputados/data_importer/session.py
pygov_br/django_apps/camara_deputados/migrations/0001_initial.py
pygov_br/django_apps/camara_deputados/migrations/0002_auto_20170719_2250.py
pygov_br/django_apps/camara_deputados/migrations/0003_auto_20170719_2307.py
pygov_br/django_apps/camara_deputados/migrations/0004_auto_20170719_2314.py
pygov_br/django_apps/camara_deputados/migrations/0005_auto_20170719_2330.py
pygov_br/django_apps/camara_deputados/migrations/0006_auto_20170720_2347.py
pygov_br/django_apps/camara_deputados/migrations/__init__.py
pygov_br/tests/__init__.py
pygov_br/tests/__main__.py
pygov_br/tests/test_base.py
pygov_br/tests/test_documentation.py
pygov_br/tests/camara_deputados/__init__.py
pygov_br/tests/camara_deputados/test_deputy.py
pygov_br/tests/camara_deputados/test_legislative_body.py
pygov_br/tests/camara_deputados/test_proposal.py
pygov_br/tests/camara_deputados/test_session.py
pygov_br/vendor/__init__.py
pygov_br/vendor/pyth/__init__.py
pygov_br/vendor/pyth/document.py
pygov_br/vendor/pyth/errors.py
pygov_br/vendor/pyth/format.py
pygov_br/vendor/pyth/encodings/__init__.py
pygov_br/vendor/pyth/encodings/symbol.py
pygov_br/vendor/pyth/plugins/__init__.py
pygov_br/vendor/pyth/plugins/latex/__init__.py
pygov_br_mj-0.1.0.dist-info/LICENSE
pygov_br_mj-0.1.0.dist-info/METADATA
pygov_br_mj-0.1.0.dist-info/WHEEL
pygov_br_mj-0.1.0.dist-info/entry_points.txt
pygov_br_mj-0.1.0.dist-info/top_level.txt
pygov_br_mj-0.1.0.dist-info/RECORD
