Metadata-Version: 2.1
Name: pygov-br-mj
Version: 0.1.0
Summary: A short description for your project.
Home-page: UNKNOWN
Author: Matheus Fernandes
Author-email: matheus.souza.fernandes@gmail.com
License: UNKNOWN
Platform: any
Classifier: Development Status :: 3 - Alpha
Classifier: Intended Audience :: Developers
Classifier: License :: OSI Approved :: GNU General Public License (GPL)
Classifier: Operating System :: POSIX
Classifier: Programming Language :: Python
Classifier: Topic :: Software Development :: Libraries
Requires-Dist: requests (>=2.11.1)
Requires-Dist: beautifulsoup4
Requires-Dist: click
Requires-Dist: pytz
Provides-Extra: dev
Requires-Dist: mock ; extra == 'dev'
Requires-Dist: responses ; extra == 'dev'
Requires-Dist: pytest ; extra == 'dev'
Requires-Dist: pytest-cov ; extra == 'dev'
Requires-Dist: coveralls ; extra == 'dev'
Requires-Dist: flake8 ; extra == 'dev'
Requires-Dist: manuel ; extra == 'dev'
